ml_eis/__init__.py
ml_eis/electrochem.py
ml_eis/ml_eis.py
ml_eis/data/44_cell_cap_diff_var_1st_10cycles.csv
ml_eis/data/44_cell_cap_ret_300_cycles.csv
ml_eis/data/MLP_NN_Optimized.sav
ml_eis/data/Z1_high_f.csv
ml_eis/data/Z1max.csv
ml_eis/data/Z2_high_f.csv
ml_eis/data/Z2max.csv
ml_eis/data/freq_fit_max.csv
ml_eis/data/gradient_boosting.sav
ml_eis/data/rdf.sav
ml_eis-0.2.9.dist-info/LICENSE
ml_eis-0.2.9.dist-info/METADATA
ml_eis-0.2.9.dist-info/WHEEL
ml_eis-0.2.9.dist-info/top_level.txt
ml_eis-0.2.9.dist-info/RECORD
