Metadata-Version: 2.1
Name: ml-eis
Version: 0.2.9
Summary: data processing and machine learning model for EIS
Home-page: https://github.com/yuefan98/Machine-Learning-on-EIS
Author: Yuefan Ji
Author-email: yuefan@uw.edu
Project-URL: Bug Tracker, https://github.com/yuefan98/Machine-Learning-on-EIS
Classifier: Programming Language :: Python :: 3
Classifier: License :: OSI Approved :: MIT License
Classifier: Operating System :: OS Independent
Requires-Python: >=3.6
License-File: LICENSE
